{"2134":{"depart":"楊梅中山北","two":"桃竹處","one":"桃竹處楊梅區","name":"徐泰宇","reason":"職災假"},"1801287":{"depart":"新竹市北區南寮店","two":"桃竹處","one":"桃竹處新竹區","name":"曾映寧","reason":"育嬰留停"},"1910729":{"depart":"新竹縣竹東鎮北興店","two":"桃竹處","one":"桃竹處竹東區","name":"楊雨君","reason":"育嬰留停"},"2007942":{"depart":"新竹縣湖口鄉和愛店","two":"桃竹處","one":"桃竹處湖北區","name":"羅葦倫","reason":"育嬰留停"},"2012642":{"depart":"竹北隘口店","two":"桃竹處","one":"桃竹處竹北區","name":"翁偉強","reason":"育嬰留停"},"2014572":{"depart":"新竹縣湖口鄉中山店","two":"桃竹處","one":"桃竹處湖北區","name":"邱畇霏","reason":"育嬰留停"},"2103376":{"depart":"新竹縣關西鎮北平店","two":"桃竹處","one":"桃竹處竹北區","name":"羅雁方","reason":"育嬰留停"},"2103419":{"depart":"桃園市平鎮區龍南店","two":"桃竹處","one":"桃竹處平鎮區","name":"鍾晴","reason":"育嬰留停"},"2104542":{"depart":"桃園縣龍潭鄉中興店(新)","two":"桃竹處","one":"桃竹處大龍區","name":"董怡君","reason":"育嬰留停"},"2107781":{"depart":"桃園市八德區東勇店","two":"桃竹處","one":"桃竹處南桃區","name":"李玦瑩","reason":"育嬰留停"},"2111873":{"depart":"新竹市香山區香北店","two":"桃竹處","one":"桃竹處新竹區","name":"陳怡雯","reason":"產假"},"2111955":{"depart":"楊梅新農店","two":"桃竹處","one":"桃竹處楊梅區","name":"古家瑜","reason":"產假"},"2112970":{"depart":"竹北勝利店","two":"桃竹處","one":"桃竹處竹北區","name":"黎世翔","reason":"當兵"},"2113173":{"depart":"楊梅新農店","two":"桃竹處","one":"桃竹處楊梅區","name":"黃妍柔","reason":"癌症假"},"2116853":{"depart":"桃園市中壢區廣州店","two":"桃竹處","one":"桃竹處中壢區","name":"陳姿妘","reason":"育嬰留停"},"2117922":{"depart":"桃園縣龍潭鄉中興店(新)","two":"桃竹處","one":"桃竹處大龍區","name":"黃凱薇","reason":"育嬰留停"},"2200636":{"depart":"桃園縣中壢市忠孝店","two":"桃竹處","one":"桃竹處南桃區","name":"陳虹云","reason":"病假"},"2204402":{"depart":"新竹縣竹北市十興店","two":"桃竹處","one":"桃竹處竹北區","name":"呂珮菁","reason":"育嬰留停"},"2207132":{"depart":"桃園市桃園區桃鶯店","two":"桃竹處","one":"桃竹處南桃區","name":"詹明龍","reason":"育嬰留停"},"2207381":{"depart":"桃園市平鎮區祥安店","two":"桃竹處","one":"桃竹處平鎮區","name":"徐若瑄","reason":"育嬰留停"},"2216361":{"depart":"新竹市東區林森店","two":"桃竹處","one":"桃竹處新竹區","name":"鄭任純","reason":"育嬰留停"},"2300817":{"depart":"桃園市大園區春德店","two":"桃竹處","one":"桃竹處蘆竹區","name":"嚴慈寧","reason":"育嬰留停"},"2300859":{"depart":"桃園市八德區興豐店","two":"桃竹處","one":"桃竹處大龍區","name":"葉宗翰","reason":"育嬰留停"},"2302951":{"depart":"桃園市平鎮區龍南店","two":"桃竹處","one":"桃竹處平鎮區","name":"彭紫薇","reason":"產假"},"2304363":{"depart":"桃園市大園區春德店","two":"桃竹處","one":"桃竹處蘆竹區","name":"呂淑稜","reason":"育嬰留停"},"2310028":{"depart":"桃園國際","two":"桃竹處","one":"桃竹處南桃區","name":"蕭又明","reason":"當兵"},"2310779":{"depart":"新竹縣竹東鎮北興店","two":"桃竹處","one":"桃竹處竹東區","name":"游雁茹","reason":"產假"},"2311058":{"depart":"新竹縣竹北市中華店","two":"桃竹處","one":"桃竹處湖北區","name":"陳高煜","reason":"當兵"},"2400147":{"depart":"新豐振興","two":"桃竹處","one":"桃竹處湖北區","name":"翁銘駿","reason":"當兵"},"2402115":{"depart":"楊梅中山北","two":"桃竹處","one":"桃竹處楊梅區","name":"高浩棠","reason":"職災假"},"2411880":{"depart":"桃園市楊梅區梅獅店","two":"桃竹處","one":"桃竹處楊梅區","name":"邱姿穎","reason":"其他"},"2411954":{"depart":"新竹市北區西大店","two":"桃竹處","one":"桃竹處新竹區","name":"陳群","reason":"其他"},"2412101":{"depart":"桃園市中壢區領航店","two":"桃竹處","one":"桃竹處蘆竹區","name":"鍾智康","reason":"其他"},"2412231":{"depart":"桃園市楊梅區民族店","two":"桃竹處","one":"桃竹處楊梅區","name":"金麗明","reason":"其他"},"2412412":{"depart":"桃園市中壢區環東店","two":"桃竹處","one":"桃竹處中壢區","name":"羅彩玉","reason":"其他"},"2412582":{"depart":"新竹縣竹北市勝利店","two":"桃竹處","one":"桃竹處竹北區","name":"張煜晨","reason":"其他"},"2412623":{"depart":"桃園市中壢區環西店","two":"桃竹處","one":"桃竹處中壢區","name":"廖佳玉","reason":"其他"},"2412701":{"depart":"桃園縣大園鄉華興店","two":"桃竹處","one":"桃竹處蘆竹區","name":"賴蕙婷","reason":"其他"},"2412796":{"depart":"桃園市蘆竹區興福店","two":"桃竹處","one":"桃竹處北桃區","name":"巫宇謙","reason":"其他"},"2412893":{"depart":"桃園市中壢區普忠店","two":"桃竹處","one":"桃竹處中壢區","name":"王浩軒","reason":"其他"},"2412961":{"depart":"新竹縣竹北市隘口店","two":"桃竹處","one":"桃竹處竹北區","name":"郭明修","reason":"其他"},"2413109":{"depart":"桃園縣蘆竹鄉大竹店","two":"桃竹處","one":"桃竹處北桃區","name":"劉昕瑜","reason":"其他"},"2413123":{"depart":"桃園縣八德市福國北店","two":"桃竹處","one":"桃竹處大龍區","name":"黃奕嘉","reason":"其他"},"2413200":{"depart":"桃園市平鎮區延平店","two":"桃竹處","one":"桃竹處平鎮區","name":"宋梓鈺","reason":"其他"},"2413205":{"depart":"新竹縣竹北市隘口店","two":"桃竹處","one":"桃竹處竹北區","name":"徐楷芬","reason":"其他"},"2413245":{"depart":"新竹縣竹北市自強南店","two":"桃竹處","one":"桃竹處竹北區","name":"魏郁蓁","reason":"其他"},"2413310":{"depart":"新竹縣竹北市莊敬南店","two":"桃竹處","one":"桃竹處竹北區","name":"蘇泓銓","reason":"其他"},"2413386":{"depart":"新竹市北區武陵店","two":"桃竹處","one":"桃竹處新竹區","name":"王惠娜","reason":"其他"},"2413405":{"depart":"桃園縣中壢市中原店","two":"桃竹處","one":"桃竹處中壢區","name":"胡瑞珍","reason":"其他"},"2413407":{"depart":"新竹市北區武陵店","two":"桃竹處","one":"桃竹處新竹區","name":"林舒瑜","reason":"其他"},"2413417":{"depart":"新竹市東區南大店","two":"桃竹處","one":"桃竹處竹東區","name":"王彥程","reason":"其他"},"2413425":{"depart":"新竹縣竹北市中正東店","two":"桃竹處","one":"桃竹處湖北區","name":"曾彥慈","reason":"其他"},"2413463":{"depart":"桃園縣桃園市慈文店","two":"桃竹處","one":"桃竹處北桃區","name":"鄭秀芬","reason":"其他"},"2413480":{"depart":"桃園市中壢區龍智店","two":"桃竹處","one":"桃竹處中壢區","name":"鄭昀杰","reason":"其他"},"2413491":{"depart":"桃園市大園區春德店","two":"桃竹處","one":"桃竹處蘆竹區","name":"陳聖翔","reason":"其他"},"2413514":{"depart":"桃園縣桃園市永安店(新)","two":"桃竹處","one":"桃竹處北桃區","name":"張美雲","reason":"其他"},"2413517":{"depart":"桃園縣觀音鄉大觀店","two":"桃竹處","one":"桃竹處楊梅區","name":"賴盈如","reason":"其他"},"2413518":{"depart":"桃園縣觀音鄉大觀店","two":"桃竹處","one":"桃竹處楊梅區","name":"鍾青春","reason":"其他"},"2413547":{"depart":"新竹縣竹北市十興店","two":"桃竹處","one":"桃竹處竹北區","name":"劉淑鈴","reason":"其他"},"2413579":{"depart":"新竹縣竹北市嘉豐店","two":"桃竹處","one":"桃竹處竹北區","name":"李宇軒","reason":"其他"},"0204217":{"depart":"桃園縣大溪鎮僑愛店","two":"桃竹處","one":"桃竹處大龍區","name":"蔡育如","reason":"育嬰留停"},"0101522":{"depart":"桃園縣大溪鎮中正店","two":"桃竹處","one":"桃竹處大龍區","name":"簡世華","reason":"病假"},"0188415":{"depart":"新竹縣竹北市自強南店","two":"桃竹處","one":"桃竹處竹北區","name":"張珈語","reason":"育嬰留停"},"0192195":{"depart":"新竹縣竹北市勝利店","two":"桃竹處","one":"桃竹處竹北區","name":"陳芳瑜","reason":"產假"},"0197358":{"depart":"桃園桃鶯","two":"桃竹處","one":"桃竹處南桃區","name":"曾文勝","reason":"其他"},"0116142":{"depart":"新竹市北區城北店","two":"桃竹處","one":"桃竹處新竹區","name":"周秀琴","reason":"病假"},"0203916":{"depart":"新竹市東區林森店","two":"桃竹處","one":"桃竹處新竹區","name":"黃佩怡","reason":"育嬰留停"},"0101086":{"depart":"桃園縣觀音鄉大觀店","two":"桃竹處","one":"桃竹處楊梅區","name":"陳美樺","reason":"育嬰留停"}}